ouroboros/__init__.py
ouroboros/__main__.py
open_ouroboros-0.2.2.dist-info/LICENSE
open_ouroboros-0.2.2.dist-info/METADATA
open_ouroboros-0.2.2.dist-info/WHEEL
open_ouroboros-0.2.2.dist-info/entry_points.txt
open_ouroboros-0.2.2.dist-info/top_level.txt
open_ouroboros-0.2.2.dist-info/RECORD
