Metadata-Version: 2.1
Name: open-ouroboros
Version: 0.2.2
Summary: A terminal-based snake game
Home-page: https://github.com/terminal-based-games/ouroboros
Author: Carissa & Mack
Author-email: cwood@pdx.edu
License: MIT License
Platform: UNKNOWN
